PyModulationPlutoSDR/PyModulace.py
PyModulationPlutoSDR/PySDR.py
PyModulationPlutoSDR/TxRxModul.py
PyModulationPlutoSDR/__init__.py
PyModulationPlutoSDR-1.0.4.dist-info/LICENSE
PyModulationPlutoSDR-1.0.4.dist-info/METADATA
PyModulationPlutoSDR-1.0.4.dist-info/WHEEL
PyModulationPlutoSDR-1.0.4.dist-info/top_level.txt
PyModulationPlutoSDR-1.0.4.dist-info/RECORD
