Metadata-Version: 2.1
Name: PyModulationPlutoSDR
Version: 1.0.4
Summary: Will be added
Home-page: https://github.com/jiCejka/PyModulationPlutoSDR.git
Author: jiCejka
Author-email: jirka.cejka@email.cz
Project-URL: Bug Tracker, https://github.com/jiCejka/PyModulationPlutoSDR/issues
Classifier: Programming Language :: Python :: 3
Requires-Python: >=3.9
License-File: LICENSE
Requires-Dist: matplotlib (>=3.5.1)
Requires-Dist: numpy (>=1.22.3)
Requires-Dist: pyadi-iio (>=0.0.12)
Requires-Dist: pylibiio (>=0.23.1)
Requires-Dist: PyQt5 (>=5.15.6)
Requires-Dist: pyqtgraph (>=0.12.4)
Requires-Dist: scipy (>=1.8.0)
